[
	{
		"name": "Lantaka (Filipinas)",
		"unitType": "Siege",
		"replaces": "Trebuchet",
		"uniqueTo": "Filipinas",
		"movement": 2,
		"strength": 15,
		"rangedStrength": 21,
		"cost": 185,
		"requiredTech": "Physics",
		"requiredResource": "Copper",
		"upgradesTo": "Artillery",
		"obsoleteTech": "Dynamite",
		"uniques": ["Bonus vs City 200%","No defensive terrain bonus","Must set up to ranged attack"],
		"promotions": ["Volley","Extended Range","Indirect Fire"],
		"hurryCostModifier": 20,
		"attackSound": "cannon"
	},
	{
		"name": "Lantaka (Sultanate of Sulu)",
		"unitType": "Siege",
		"replaces": "Trebuchet",
		"uniqueTo": "Sultanate of Sulu",
		"movement": 2,
		"strength": 15,
		"rangedStrength": 21,
		"cost": 185,
		"requiredTech": "Physics",
		"requiredResource": "Copper",
		"upgradesTo": "Artillery",
		"obsoleteTech": "Dynamite",
		"uniques": ["Bonus vs City 200%","No defensive terrain bonus","Must set up to ranged attack"],
		"promotions": ["Volley","Extended Range","Indirect Fire"],
		"hurryCostModifier": 20,
		"attackSound": "cannon"
	},
	{
		"name": "Lantaka (Philippines)",
		"unitType": "Siege",
		"replaces": "Trebuchet",
		"uniqueTo": "Philippines",
		"movement": 2,
		"strength": 15,
		"rangedStrength": 21,
		"cost": 185,
		"requiredTech": "Physics",
		"requiredResource": "Copper",
		"upgradesTo": "Artillery",
		"obsoleteTech": "Dynamite",
		"uniques": ["Bonus vs City 200%","No defensive terrain bonus","Must set up to ranged attack"],
		"promotions": ["Volley","Extended Range","Indirect Fire"],
		"hurryCostModifier": 20,
		"attackSound": "cannon"
	},
	{
		"name": "Lantaka (Tondo)",
		"unitType": "Siege",
		"replaces": "Trebuchet",
		"uniqueTo": "Tondo",
		"movement": 2,
		"strength": 15,
		"rangedStrength": 21,
		"cost": 185,
		"requiredTech": "Physics",
		"requiredResource": "Copper",
		"upgradesTo": "Artillery",
		"obsoleteTech": "Dynamite",
		"uniques": ["Bonus vs City 200%","No defensive terrain bonus","Must set up to ranged attack"],
		"promotions": ["Volley","Extended Range","Indirect Fire"],
		"hurryCostModifier": 20,
		"attackSound": "cannon"
	},
	{
		"name": "Arcabuceros de Pampanga",
		"unitType": "Gunpowder",
		"replaces": "Musketman",
		"uniqueTo": "Filipinas",
		"movement": 2,
		"strength": 25,
		"cost": 150,
		"requiredTech": "Gunpowder",
		"upgradesTo": "Rifleman",
		"obsoleteTech": "Rifling",
		"attackSound": "shot"
	},
	{
		"name": "Mappiang Bayani",
		"unitType": "Gunpowder",
		"replaces": "Musketman",
		"uniqueTo": "Tondo",
		"movement": 2,
		"strength": 25,
		"cost": 150,
		"requiredTech": "Gunpowder",
		"upgradesTo": "Rifleman",
		"obsoleteTech": "Rifling",
		"attackSound": "shot"
	},
]
